dday-1.0.1.dist-info/METADATA
dday-1.0.1.dist-info/WHEEL
dday-1.0.1.dist-info/entry_points.txt
dday/__init__.py
dday/dday.py
dday-1.0.1.dist-info/RECORD
